{
    "instrumentation_voicing": "solo vocal without accompaniment", 
    "form": [
        {
            "attribute_key": "sarki", 
            "mb_attribute": "\u015eark\u0131", 
            "source": "http://musicbrainz.org/work/0ffe2ca5-65c0-4d6e-bdb2-d9e7d288176f"
        }, 
        {
            "attribute_key": "sarki", 
            "mb_tag": "\u015fark\u0131", 
            "source": "http://musicbrainz.org/recording/bc02199b-4126-47ca-be2a-04b78959997b"
        }
    ], 
    "releases": [
        {
            "mbid": "5a62f3a6-69c6-4237-87fb-f5163a9d070e", 
            "title": "Canl\u0131 Fas\u0131l 9 - Saba"
        }
    ], 
    "title": "Bir Esmere G\u00f6n\u00fcl Verdim", 
    "url": "http://musicbrainz.org/work/bc02199b-4126-47ca-be2a-04b78959997b", 
    "artist_credits": [
        {
            "mbid": "ef074ab6-a2a8-42f7-a454-068265023697", 
            "name": "Aziz T\u00fcrk Sanat M\u00fczi\u011fi Grubu"
        }
    ], 
    "mbid": "bc02199b-4126-47ca-be2a-04b78959997b", 
    "sampling_frequency": 44100, 
    "works": [
        {
            "mbid": "0ffe2ca5-65c0-4d6e-bdb2-d9e7d288176f", 
            "title": "Bir Esmere G\u00f6n\u00fcl Verdim"
        }
    ], 
    "makam": [
        {
            "attribute_key": "saba", 
            "mb_attribute": "Saba", 
            "source": "http://musicbrainz.org/work/0ffe2ca5-65c0-4d6e-bdb2-d9e7d288176f"
        }, 
        {
            "attribute_key": "saba", 
            "mb_tag": "saba", 
            "source": "http://musicbrainz.org/recording/bc02199b-4126-47ca-be2a-04b78959997b"
        }
    ], 
    "artists": [
        {
            "mbid": "ef074ab6-a2a8-42f7-a454-068265023697", 
            "attribute-list": [
                "choir vocals"
            ], 
            "type": "vocal", 
            "name": "Aziz T\u00fcrk Sanat M\u00fczi\u011fi Grubu"
        }
    ], 
    "duration": 88, 
    "path": "../data/Saba/bc02199b-4126-47ca-be2a-04b78959997b.mp3", 
    "usul": [
        {
            "attribute_key": "aksak", 
            "mb_attribute": "Aksak", 
            "source": "http://musicbrainz.org/work/0ffe2ca5-65c0-4d6e-bdb2-d9e7d288176f"
        }, 
        {
            "attribute_key": "aksak", 
            "mb_tag": "aksak", 
            "source": "http://musicbrainz.org/recording/bc02199b-4126-47ca-be2a-04b78959997b"
        }
    ], 
    "bit_rate": 160
}