{
    "instrumentation_voicing": "solo vocal with accompaniment", 
    "form": [
        {
            "attribute_key": "turku", 
            "mb_attribute": "T\u00fcrk\u00fc", 
            "source": "http://musicbrainz.org/work/84d98f0c-6b4f-4485-a453-7fb99e87a56e"
        }, 
        {
            "attribute_key": "sarki", 
            "mb_tag": "\u015fark\u0131", 
            "source": "http://musicbrainz.org/recording/c79290ea-2b38-41d1-ae53-bce6c12682d1"
        }
    ], 
    "releases": [
        {
            "mbid": "6add5018-3c05-46f0-a982-9ea57b8bce36", 
            "title": "Sizden Biri"
        }
    ], 
    "title": "A\u00e7\u0131l\u0131r Gonca G\u00fcl Yar", 
    "url": "http://musicbrainz.org/work/c79290ea-2b38-41d1-ae53-bce6c12682d1", 
    "artist_credits": [
        {
            "mbid": "cd8fb8c7-a01a-40b1-ae98-f69ef5686b28", 
            "name": "Melda Kuyucu"
        }
    ], 
    "mbid": "c79290ea-2b38-41d1-ae53-bce6c12682d1", 
    "sampling_frequency": 44100, 
    "works": [
        {
            "mbid": "84d98f0c-6b4f-4485-a453-7fb99e87a56e", 
            "title": "A\u00e7\u0131l\u0131r Gonca G\u00fcl Yar"
        }
    ], 
    "makam": [
        {
            "attribute_key": "segah", 
            "mb_attribute": "Segah", 
            "source": "http://musicbrainz.org/work/84d98f0c-6b4f-4485-a453-7fb99e87a56e"
        }, 
        {
            "attribute_key": "segah", 
            "mb_tag": "segah", 
            "source": "http://musicbrainz.org/recording/c79290ea-2b38-41d1-ae53-bce6c12682d1"
        }
    ], 
    "artists": [
        {
            "mbid": "125ec42a-7229-4250-afc5-e057484327fe", 
            "type": "performing orchestra", 
            "name": "[unknown]"
        }, 
        {
            "mbid": "cd8fb8c7-a01a-40b1-ae98-f69ef5686b28", 
            "type": "vocal", 
            "name": "Melda Kuyucu"
        }
    ], 
    "duration": 139, 
    "path": "../data/Segah/c79290ea-2b38-41d1-ae53-bce6c12682d1.mp3", 
    "usul": [
        {
            "attribute_key": "nimsofyan", 
            "mb_attribute": "Nimsofyan", 
            "source": "http://musicbrainz.org/work/84d98f0c-6b4f-4485-a453-7fb99e87a56e"
        }, 
        {
            "attribute_key": "nimsofyan", 
            "mb_tag": "nimsofyan", 
            "source": "http://musicbrainz.org/recording/c79290ea-2b38-41d1-ae53-bce6c12682d1"
        }
    ], 
    "bit_rate": 64
}